bmh_update_ueq/__init__.py
bmh_update_ueq-0.1.dist-info/DESCRIPTION.rst
bmh_update_ueq-0.1.dist-info/METADATA
bmh_update_ueq-0.1.dist-info/RECORD
bmh_update_ueq-0.1.dist-info/WHEEL
bmh_update_ueq-0.1.dist-info/metadata.json
bmh_update_ueq-0.1.dist-info/top_level.txt
