Metadata-Version: 2.0
Name: bmh-update-ueq
Version: 0.1
Summary: A purpose made script using docx and pandas to import the content from docx forms and store it within a csv file
Home-page: http://github.com/flibbble/bmh_update_ueq
Author: D Levin
Author-email: flibbble@gmail.com
License: MIT
Platform: UNKNOWN
Requires-Dist: docx
Requires-Dist: pandas
